{
    "family": {
        "parents": {
            "s12": 0,
            "s23": 0,
            "s13": 0
        },

        "siblings": {
            "s12": 0,
            "s23": 0,
            "s13": 0
        }
    },
    "SO": {
        "gf/w": {
            "s12": 0,
            "s23": 0,
            "s13": 0
        },

        "bf/h": {
            "s12": 0,
            "s23": 0,
            "s13": 0
        }
    },
    "friend": {
        "close": {
            "s12": 0,
            "s23": 0,
            "s13": 0
        },

        "distant": {
            "s12": 0,
            "s23": 0,
            "s13": 0
        }
    },
    "professional": {
        "team": {
            "s12": 0,
            "s23": 0,
            "s13": 0
        },

        "customer": {
            "s12": 0,
            "s23": 0,
            "s13": 0
        }
    }
}